<annotation>
	<folder>images</folder>
	<filename>46_042020-09-08 15-35-09-509-1.png</filename>
	<path>C:\Users\vitek007718\Desktop\vid_test\images\46_042020-09-08 15-35-09-509-1.png</path>
	<source>
		<database>Unknown</database>
	</source>
	<size>
		<width>1920</width>
		<height>1080</height>
		<depth>3</depth>
	</size>
	<segmented>0</segmented>
	<object>
		<name>person</name>
		<pose>Unspecified</pose>
		<truncated>0</truncated>
		<difficult>0</difficult>
		<bndbox>
			<xmin>64</xmin>
			<ymin>270</ymin>
			<xmax>889</xmax>
			<ymax>782</ymax>
		</bndbox>
	</object>
</annotation>
